niraapad/__init__.py
niraapad/backends.py
niraapad/data_processing/commands.py
niraapad/data_processing/curation.py
niraapad/detective/detector.py
niraapad/detective/engine.py
niraapad/detective/user_interface.py
niraapad/keys/ispy_cs_ubc_ca/server.crt
niraapad/keys/ispy_cs_ubc_ca/server.key
niraapad/keys/localhost/server.crt
niraapad/keys/localhost/server.key
niraapad/lab_computer/__init__.py
niraapad/lab_computer/niraapad_client.py
niraapad/lab_computer/niraapad_replay_client.py
niraapad/middlebox/__init__.py
niraapad/middlebox/niraapad_server.py
niraapad/middlebox/start_server.py
niraapad/protos/__init__.py
niraapad/protos/niraapad_pb2.py
niraapad/protos/niraapad_pb2_grpc.py
niraapad/shared/__init__.py
niraapad/shared/tracing.py
niraapad/shared/utils.py
niraapad/test/__init__.py
niraapad/test/test_IDS.py
niraapad/test/test_deck.py
niraapad/test/test_niraapad.py
niraapad-1.5.6.dist-info/LICENSE
niraapad-1.5.6.dist-info/METADATA
niraapad-1.5.6.dist-info/WHEEL
niraapad-1.5.6.dist-info/top_level.txt
niraapad-1.5.6.dist-info/RECORD
