Metadata-Version: 2.1
Name: niraapad
Version: 1.5.6
Summary: A library that routes all communication to the N9 and UR3 robots via a secure middlebox.
Home-page: https://github.com/ubc-systopia/cps-security-code
Author: Arpan Gujarati
Author-email: arpanbg@cs.ubc.ca
License: MIT
Platform: UNKNOWN
Requires-Python: >=3.6.0
License-File: LICENSE
